hayasaka/__init__.py
hayasaka/__main__.py
hayasaka/cli.py
hayasaka/core.py
hayasaka-0.2.0.dist-info/LICENSE
hayasaka-0.2.0.dist-info/METADATA
hayasaka-0.2.0.dist-info/WHEEL
hayasaka-0.2.0.dist-info/entry_points.txt
hayasaka-0.2.0.dist-info/top_level.txt
hayasaka-0.2.0.dist-info/RECORD
